[
  {
    "id": "casa-seat-01",
    "author": "Nagore Suárez",
    "book": "",
    "publisher": "",
    "location": "CASA SEAT",
    "address": "Passeig de Gràcia, 38",
    "coordinates": { "lat": 41.3920, "lng": 2.1650 },
    "startTime": "10:00",
    "endTime": "11:00"
  },
  {
    "id": "casa-seat-02",
    "author": "Beatriz Roger",
    "book": "",
    "publisher": "",
    "location": "CASA SEAT",
    "address": "Passeig de Gràcia, 38",
    "coordinates": { "lat": 41.3920, "lng": 2.1650 },
    "startTime": "10:00",
    "endTime": "11:00"
  },
  {
    "id": "casa-seat-03",
    "author": "Luiso Soldevila",
    "book": "",
    "publisher": "",
    "location": "CASA SEAT",
    "address": "Passeig de Gràcia, 38",
    "coordinates": { "lat": 41.3920, "lng": 2.1650 },
    "startTime": "10:00",
    "endTime": "11:00"
  },
  {
    "id": "casa-seat-04",
    "author": "Supersubmarina",
    "book": "",
    "publisher": "",
    "location": "CASA SEAT",
    "address": "Passeig de Gràcia, 38",
    "coordinates": { "lat": 41.3920, "lng": 2.1650 },
    "startTime": "11:00",
    "endTime": "14:00"
  },
  {
    "id": "casa-seat-05",
    "author": "Ángela Quintas",
    "book": "",
    "publisher": "",
    "location": "CASA SEAT",
    "address": "Passeig de Gràcia, 38",
    "coordinates": { "lat": 41.3920, "lng": 2.1650 },
    "startTime": "11:00",
    "endTime": "12:00"
  },
  {
    "id": "casa-seat-06",
    "author": "Iker Ruiz",
    "book": "",
    "publisher": "",
    "location": "CASA SEAT",
    "address": "Passeig de Gràcia, 38",
    "coordinates": { "lat": 41.3920, "lng": 2.1650 },
    "startTime": "11:00",
    "endTime": "12:00"
  },
  {
    "id": "casa-seat-07",
    "author": "Carolina Iglesias",
    "book": "",
    "publisher": "",
    "location": "CASA SEAT",
    "address": "Passeig de Gràcia, 38",
    "coordinates": { "lat": 41.3920, "lng": 2.1650 },
    "startTime": "11:00",
    "endTime": "12:00"
  },
  {
    "id": "casa-seat-08",
    "author": "Jesús Cañadas",
    "book": "",
    "publisher": "",
    "location": "CASA SEAT",
    "address": "Passeig de Gràcia, 38",
    "coordinates": { "lat": 41.3920, "lng": 2.1650 },
    "startTime": "12:00",
    "endTime": "13:00"
  },
  {
    "id": "casa-seat-09",
    "author": "Arnau París",
    "book": "",
    "publisher": "",
    "location": "CASA SEAT",
    "address": "Passeig de Gràcia, 38",
    "coordinates": { "lat": 41.3920, "lng": 2.1650 },
    "startTime": "12:00",
    "endTime": "13:00"
  },
  {
    "id": "casa-seat-10",
    "author": "Manuel Loureiro",
    "book": "",
    "publisher": "",
    "location": "CASA SEAT",
    "address": "Passeig de Gràcia, 38",
    "coordinates": { "lat": 41.3920, "lng": 2.1650 },
    "startTime": "13:00",
    "endTime": "14:00"
  },
  {
    "id": "casa-seat-11",
    "author": "Santi Giménez",
    "book": "",
    "publisher": "",
    "location": "CASA SEAT",
    "address": "Passeig de Gràcia, 38",
    "coordinates": { "lat": 41.3920, "lng": 2.1650 },
    "startTime": "13:00",
    "endTime": "14:00"
  },
  {
    "id": "casa-seat-12",
    "author": "Joan Dausà",
    "book": "",
    "publisher": "",
    "location": "CASA SEAT",
    "address": "Passeig de Gràcia, 38",
    "coordinates": { "lat": 41.3920, "lng": 2.1650 },
    "startTime": "15:30",
    "endTime": "17:00"
  },
  {
    "id": "casa-seat-13",
    "author": "Paula Monreal",
    "book": "",
    "publisher": "",
    "location": "CASA SEAT",
    "address": "Passeig de Gràcia, 38",
    "coordinates": { "lat": 41.3920, "lng": 2.1650 },
    "startTime": "16:00",
    "endTime": "17:00"
  },
  {
    "id": "casa-seat-14",
    "author": "Rosa Lucena",
    "book": "",
    "publisher": "",
    "location": "CASA SEAT",
    "address": "Passeig de Gràcia, 38",
    "coordinates": { "lat": 41.3920, "lng": 2.1650 },
    "startTime": "16:00",
    "endTime": "17:00"
  },
  {
    "id": "casa-seat-15",
    "author": "Joana Marcús",
    "book": "",
    "publisher": "",
    "location": "CASA SEAT",
    "address": "Passeig de Gràcia, 38",
    "coordinates": { "lat": 41.3920, "lng": 2.1650 },
    "startTime": "17:00",
    "endTime": "20:00"
  },
  {
    "id": "casa-seat-16",
    "author": "Mikecrack, Timba VK, Trollino",
    "book": "",
    "publisher": "",
    "location": "CASA SEAT",
    "address": "Passeig de Gràcia, 38",
    "coordinates": { "lat": 41.3920, "lng": 2.1650 },
    "startTime": "17:00",
    "endTime": "19:00"
  },
  {
    "id": "casa-seat-17",
    "author": "Andrea Longarela",
    "book": "",
    "publisher": "",
    "location": "CASA SEAT",
    "address": "Passeig de Gràcia, 38",
    "coordinates": { "lat": 41.3920, "lng": 2.1650 },
    "startTime": "18:00",
    "endTime": "20:00"
  },
  {
    "id": "casa-seat-18",
    "author": "Vicente Garrido",
    "book": "",
    "publisher": "",
    "location": "CASA SEAT",
    "address": "Passeig de Gràcia, 38",
    "coordinates": { "lat": 41.3920, "lng": 2.1650 },
    "startTime": "19:00",
    "endTime": "20:00"
  },
  {
    "id": "casa-seat-19",
    "author": "Nahir Gutiérrez",
    "book": "",
    "publisher": "",
    "location": "CASA SEAT",
    "address": "Passeig de Gràcia, 38",
    "coordinates": { "lat": 41.3920, "lng": 2.1650 },
    "startTime": "19:00",
    "endTime": "20:00"
  },
  {
    "id": "anagrama-01",
    "author": "Irene Solà",
    "book": "",
    "publisher": "Anagrama",
    "location": "Per confirmar",
    "address": "",
    "coordinates": { "lat": 41.3874, "lng": 2.1686 },
    "startTime": "",
    "endTime": ""
  },
  {
    "id": "anagrama-02",
    "author": "Milena Busquets",
    "book": "",
    "publisher": "Anagrama",
    "location": "Per confirmar",
    "address": "",
    "coordinates": { "lat": 41.3874, "lng": 2.1686 },
    "startTime": "",
    "endTime": ""
  },
  {
    "id": "anagrama-03",
    "author": "Marina Garcés",
    "book": "",
    "publisher": "Anagrama",
    "location": "Per confirmar",
    "address": "",
    "coordinates": { "lat": 41.3874, "lng": 2.1686 },
    "startTime": "",
    "endTime": ""
  },
  {
    "id": "anagrama-04",
    "author": "Lucía Lijtmaer",
    "book": "",
    "publisher": "Anagrama",
    "location": "Per confirmar",
    "address": "",
    "coordinates": { "lat": 41.3874, "lng": 2.1686 },
    "startTime": "",
    "endTime": ""
  },
  {
    "id": "anagrama-05",
    "author": "Imma Monsó",
    "book": "",
    "publisher": "Anagrama",
    "location": "Per confirmar",
    "address": "",
    "coordinates": { "lat": 41.3874, "lng": 2.1686 },
    "startTime": "",
    "endTime": ""
  },
  {
    "id": "anagrama-06",
    "author": "Pol Guasch",
    "book": "",
    "publisher": "Anagrama",
    "location": "Per confirmar",
    "address": "",
    "coordinates": { "lat": 41.3874, "lng": 2.1686 },
    "startTime": "",
    "endTime": ""
  },
  {
    "id": "anagrama-07",
    "author": "Sergi Pàmies",
    "book": "",
    "publisher": "Anagrama",
    "location": "Per confirmar",
    "address": "",
    "coordinates": { "lat": 41.3874, "lng": 2.1686 },
    "startTime": "",
    "endTime": ""
  },
  {
    "id": "anagrama-08",
    "author": "Anna Pacheco",
    "book": "",
    "publisher": "Anagrama",
    "location": "Per confirmar",
    "address": "",
    "coordinates": { "lat": 41.3874, "lng": 2.1686 },
    "startTime": "",
    "endTime": ""
  },
  {
    "id": "anagrama-09",
    "author": "Hernán Díaz",
    "book": "",
    "publisher": "Anagrama",
    "location": "Per confirmar",
    "address": "",
    "coordinates": { "lat": 41.3874, "lng": 2.1686 },
    "startTime": "",
    "endTime": ""
  },
  {
    "id": "anagrama-10",
    "author": "Juan Pablo Villalobos",
    "book": "",
    "publisher": "Anagrama",
    "location": "Per confirmar",
    "address": "",
    "coordinates": { "lat": 41.3874, "lng": 2.1686 },
    "startTime": "",
    "endTime": ""
  },
  {
    "id": "anagrama-11",
    "author": "Berta García Faet",
    "book": "",
    "publisher": "Anagrama",
    "location": "Per confirmar",
    "address": "",
    "coordinates": { "lat": 41.3874, "lng": 2.1686 },
    "startTime": "",
    "endTime": ""
  },
  {
    "id": "anagrama-12",
    "author": "Andrea Genovart",
    "book": "",
    "publisher": "Anagrama",
    "location": "Per confirmar",
    "address": "",
    "coordinates": { "lat": 41.3874, "lng": 2.1686 },
    "startTime": "",
    "endTime": ""
  },
  {
    "id": "anagrama-13",
    "author": "Mercè Ibarz",
    "book": "",
    "publisher": "Anagrama",
    "location": "Per confirmar",
    "address": "",
    "coordinates": { "lat": 41.3874, "lng": 2.1686 },
    "startTime": "",
    "endTime": ""
  },
  {
    "id": "anagrama-14",
    "author": "Lluís Calvo",
    "book": "",
    "publisher": "Anagrama",
    "location": "Per confirmar",
    "address": "",
    "coordinates": { "lat": 41.3874, "lng": 2.1686 },
    "startTime": "",
    "endTime": ""
  },
  {
    "id": "anagrama-15",
    "author": "Luna Miguel",
    "book": "",
    "publisher": "Anagrama",
    "location": "Per confirmar",
    "address": "",
    "coordinates": { "lat": 41.3874, "lng": 2.1686 },
    "startTime": "",
    "endTime": ""
  },
  {
    "id": "anagrama-16",
    "author": "María Sánchez",
    "book": "",
    "publisher": "Anagrama",
    "location": "Per confirmar",
    "address": "",
    "coordinates": { "lat": 41.3874, "lng": 2.1686 },
    "startTime": "",
    "endTime": ""
  },
  {
    "id": "anagrama-17",
    "author": "Clara Serra",
    "book": "",
    "publisher": "Anagrama",
    "location": "Per confirmar",
    "address": "",
    "coordinates": { "lat": 41.3874, "lng": 2.1686 },
    "startTime": "",
    "endTime": ""
  },
  {
    "id": "anagrama-18",
    "author": "Mario Obrero",
    "book": "",
    "publisher": "Anagrama",
    "location": "Per confirmar",
    "address": "",
    "coordinates": { "lat": 41.3874, "lng": 2.1686 },
    "startTime": "",
    "endTime": ""
  },
  {
    "id": "anagrama-19",
    "author": "Eloy Fernández Porta",
    "book": "",
    "publisher": "Anagrama",
    "location": "Per confirmar",
    "address": "",
    "coordinates": { "lat": 41.3874, "lng": 2.1686 },
    "startTime": "",
    "endTime": ""
  },
  {
    "id": "anagrama-20",
    "author": "Clara Queraltó",
    "book": "",
    "publisher": "Anagrama",
    "location": "Per confirmar",
    "address": "",
    "coordinates": { "lat": 41.3874, "lng": 2.1686 },
    "startTime": "",
    "endTime": ""
  },
  {
    "id": "anagrama-21",
    "author": "Michel Nieva",
    "book": "",
    "publisher": "Anagrama",
    "location": "Per confirmar",
    "address": "",
    "coordinates": { "lat": 41.3874, "lng": 2.1686 },
    "startTime": "",
    "endTime": ""
  },
  {
    "id": "anagrama-22",
    "author": "Luis López Carrasco",
    "book": "",
    "publisher": "Anagrama",
    "location": "Per confirmar",
    "address": "",
    "coordinates": { "lat": 41.3874, "lng": 2.1686 },
    "startTime": "",
    "endTime": ""
  }
]
